pinetodo/__init__.py
pinetodo/location_config.py
pinetodo/main.py
pinetodo/parse.py
pinetodo/router.py
pinetodo/core/__init__.py
pinetodo/core/cli/__init__.py
pinetodo/core/cli/add_subtask.py
pinetodo/core/cli/add_task.py
pinetodo/core/cli/delete_by_id.py
pinetodo/core/cli/delete_suptask.py
pinetodo/core/cli/download_pinedocs.py
pinetodo/core/cli/edit_by_id.py
pinetodo/core/cli/export.py
pinetodo/core/cli/functions.py
pinetodo/core/cli/id_info.py
pinetodo/core/cli/imports_tasks.py
pinetodo/core/cli/list_overdue.py
pinetodo/core/cli/list_task.py
pinetodo/core/cli/mark_done.py
pinetodo/core/cli/mark_todo.py
pinetodo/core/cli/read_docs.py
pinetodo/core/cli/search_task.py
pinetodo/core/cli/sort_tasks.py
pinetodo/core/cli/statistics.py
pinetodo-1.0.1.dist-info/licenses/LICENSE
pinetodo-1.0.1.dist-info/METADATA
pinetodo-1.0.1.dist-info/WHEEL
pinetodo-1.0.1.dist-info/entry_points.txt
pinetodo-1.0.1.dist-info/top_level.txt
pinetodo-1.0.1.dist-info/RECORD
