Metadata-Version: 2.4
Name: pinetodo
Version: 1.0.1
Summary: `PineToDo` is a tool with [CLI](https://id.wikipedia.org/wiki/Command_Line_Interface) or `Command_Line_Interface` based, designed to create and manage tasks in todo style
Home-page: https://github.com/openpineapletools/pinetodo
Author: openpineaplehub
Author-email: openpineaple@gmail.com
Project-URL: Bug Tracker, https://github.com/openpineapletools/pinetodo/issues
Project-URL: Request Features, https://github.com/openpineapletools/pinetodo/pulls
Project-URL: Documentation Pinetodo, https://openpineapletools.github.io/pinetodo/#/
Classifier: Programming Language :: Python :: 3
Classifier: Programming Language :: Python :: 3.8
Classifier: License :: OSI Approved :: MIT License
Classifier: Operating System :: OS Independent
Classifier: Environment :: Console
Classifier: Intended Audience :: Developers
Classifier: Topic :: Utilities
Requires-Python: >=3.8
License-File: LICENSE
Requires-Dist: json5
Requires-Dist: requests
Requires-Dist: rich
Dynamic: author
Dynamic: author-email
Dynamic: classifier
Dynamic: description
Dynamic: description-content-type
Dynamic: home-page
Dynamic: license-file
Dynamic: project-url
Dynamic: requires-dist
Dynamic: requires-python
Dynamic: summary
